uniworkflow/__init__.py
uniworkflow/exceptions.py
uniworkflow/main.py
uniworkflow/utils.py
uniworkflow/auth/__init__.py
uniworkflow/auth/oauth.py
uniworkflow/providers/__init__.py
uniworkflow/providers/base.py
uniworkflow/providers/coze.py
uniworkflow/providers/dify.py
uniworkflow/providers/make.py
uniworkflow/providers/n8n.py
uniworkflow/providers/zapier.py
uniworkflow-0.1.8.dist-info/LICENSE
uniworkflow-0.1.8.dist-info/METADATA
uniworkflow-0.1.8.dist-info/WHEEL
uniworkflow-0.1.8.dist-info/top_level.txt
uniworkflow-0.1.8.dist-info/RECORD
