Metadata-Version: 2.1
Name: uniworkflow
Version: 0.1.8
Summary: A Python library for integrating with various workflow providers
Home-page: https://github.com/EvalsOne/uniworkflow
Author: Quentin
Author-email: tagriver@gmail.com
Classifier: Programming Language :: Python :: 3
Classifier: License :: OSI Approved :: MIT License
Classifier: Operating System :: OS Independent
Requires-Python: >=3.6
License-File: LICENSE
Requires-Dist: requests>=2.25.1
